pyonceperday/__init__.py
pyonceperday/events.py
pyonceperday/exceptions.py
pyonceperday/tests/__init__.py
pyonceperday/tests/test_events.py
pyonceperday-0.1.3.dist-info/METADATA
pyonceperday-0.1.3.dist-info/WHEEL
pyonceperday-0.1.3.dist-info/top_level.txt
pyonceperday-0.1.3.dist-info/RECORD
