Metadata-Version: 2.4
Name: pyonceperday
Version: 0.1.3
Summary: A lil something for me
Requires-Python: >=3.11
Requires-Dist: pytest>=8.3.5
Requires-Dist: pytz>=2025.2
